urbantoygraph-1.0.1.dist-info/licenses/LICENSE
utg/__init__.py
utg/create_graph.py
utg/utils.py
utg/tests/test_create_graph.py
utg/tests/test_utils.py
urbantoygraph-1.0.1.dist-info/METADATA
urbantoygraph-1.0.1.dist-info/WHEEL
urbantoygraph-1.0.1.dist-info/top_level.txt
urbantoygraph-1.0.1.dist-info/RECORD
